PyBitgetApi/__init__.py
PyBitgetApi/client.py
PyBitgetApi/enums.py
PyBitgetApi/exceptions.py
PyBitgetApi/package_data.dat
PyBitgetApi/utils.py
PyBitgetApi-3.0.1.dist-info/METADATA
PyBitgetApi-3.0.1.dist-info/WHEEL
PyBitgetApi-3.0.1.dist-info/entry_points.txt
PyBitgetApi-3.0.1.dist-info/top_level.txt
PyBitgetApi-3.0.1.dist-info/RECORD
