Metadata-Version: 2.1
Name: PyBitgetApi
Version: 3.0.1
Summary: A sample Python project
Author-email: Joseph barracuda <josephbarracuda54@gmail.com>
Project-URL: Source, https://github.com/joseph-team/bitget-api
Requires-Python: >=3.9
